yqn_project_cli/README.md
yqn_project_cli/__init__.py
yqn_project_cli/init_project.py
yqn_project_cli/rpc/__init__.py
yqn_project_cli/rpc/mysql_.py
yqn_project_cli/rpc/odps_.py
yqn_project_cli/rpc/apollo/__init__.py
yqn_project_cli/rpc/apollo/apollo_client.py
yqn_project_cli/rpc/apollo/apollo_config.py
yqn_project_cli/rpc/eureka/__init__.py
yqn_project_cli/rpc/eureka/eureka_client.py
yqn_project_cli/rpc/eureka/eureka_request.py
yqn_project_cli/template/$template_config$py
yqn_project_cli/template/__init__.py
yqn_project_cli/template/project/$dockerignore
yqn_project_cli/template/project/$gitignore
yqn_project_cli/template/project/Dockerfile
yqn_project_cli/template/project/__init__$py
yqn_project_cli/template/project/__init__.py
yqn_project_cli/template/project/entrypoint$sh
yqn_project_cli/template/project/gunicorn_config$py
yqn_project_cli/template/project/gunicorn_config_test$py
yqn_project_cli/template/project/model_url_config_local$yml
yqn_project_cli/template/project/model_url_config_online$yml
yqn_project_cli/template/project/requirements$txt
yqn_project_cli/template/project/template_flask$py
yqn_project_cli/template/project/template_flask_local$py
yqn_project_cli/template/project/api/__init__.py
yqn_project_cli/template/project/api/main/__init__.py
yqn_project_cli/template/project/api/main/handler.py
yqn_project_cli/template/project/api/main/model.py
yqn_project_cli/template/project/api/main/parser.py
yqn_project_cli/template/project/api/main/views.py
yqn_project_cli/template/project/common/__init__.py
yqn_project_cli/template/project/config/__init__.py
yqn_project_cli/template/project/config/app.py
yqn_project_cli/template/project/rpc/__init__.py
yqn_project_cli/template/project/scripts/__init__.py
yqn_project_cli/template/project/thirds/__init__.py
yqn_project_cli/template/project/utils/__init__.py
yqn_project_cli/template/project/utils/api.py
yqn_project_cli/template/project/utils/app.py
yqn_project_cli/template/project/utils/decorators.py
yqn_project_cli-0.0.0rc89.dist-info/LICENSE
yqn_project_cli-0.0.0rc89.dist-info/METADATA
yqn_project_cli-0.0.0rc89.dist-info/WHEEL
yqn_project_cli-0.0.0rc89.dist-info/entry_points.txt
yqn_project_cli-0.0.0rc89.dist-info/top_level.txt
yqn_project_cli-0.0.0rc89.dist-info/RECORD
