Metadata-Version: 2.1
Name: yqn-project-cli
Version: 0.0.0rc89
Summary: For more faster to create semi-project based on flask
Home-page: https://blog.zoukaihua.com
Author: ZouKaihua
Author-email: zoukaihua@aliyun.com
License: UNKNOWN
Platform: UNKNOWN
Classifier: Programming Language :: Python :: 3
Classifier: License :: OSI Approved :: MIT License
Classifier: Operating System :: OS Independent
Requires-Dist: DBUtils (>=2.0)
Requires-Dist: Flask (>=1.1.2)
Requires-Dist: Flask-Compress (>=1.8.0)
Requires-Dist: Flask-Cors (>=3.0.10)
Requires-Dist: flask-restx (>=0.2.0)
Requires-Dist: PyMySQL (>=1.0.2)
Requires-Dist: pyodps (>=0.10.6)
Requires-Dist: requests (>=2.25.1)
Requires-Dist: requests-toolbelt (>=0.9.1)
Requires-Dist: termcolor (>=1.1.0)
Requires-Dist: gevent (>=20.9.0)
Requires-Dist: gunicorn (>=20.0.4)
